nanotorch/__init__.py
nanotorch/_tensor.py
nanotorch/_types.py
nanotorch/optim.py
nanotorch/version.py
nanotorch/nn/__init__.py
nanotorch/nn/_layers.py
nanotorch/nn/_losses.py
nanotorch/nn/functional.py
nanotorch-2.1.0.dist-info/LICENSE
nanotorch-2.1.0.dist-info/METADATA
nanotorch-2.1.0.dist-info/WHEEL
nanotorch-2.1.0.dist-info/top_level.txt
nanotorch-2.1.0.dist-info/RECORD
